makenote/__init__.py
makenote/cli.py
makenote/convert_old_db_to_new.py
makenote/dbmanager.py
makenote/main.py
makenote/makenote.conf
makenote/migrations.py
makenote-4.6.data/data/makenote.conf
makenote-4.6.data/scripts/makenote
makenote-4.6.dist-info/LICENSE
makenote-4.6.dist-info/METADATA
makenote-4.6.dist-info/WHEEL
makenote-4.6.dist-info/top_level.txt
makenote-4.6.dist-info/RECORD
