Metadata-Version: 2.1
Name: makenote
Version: 4.6
Summary: command line tool for quickly writing journals
Home-page: https://github.com/ekm507/makenote
Author: Erfan Kheirollahi
Author-email: ekm507@gmail.com
Keywords: makenote
License-File: LICENSE
Requires-Dist: jdatetime
Requires-Dist: prompt-toolkit
